aliyunsdkros/__init__.py
aliyunsdkros/endpoint.py
aliyunsdkros/request/__init__.py
aliyunsdkros/request/v20150901/AbandonStackRequest.py
aliyunsdkros/request/v20150901/CancelUpdateStackRequest.py
aliyunsdkros/request/v20150901/ContinueCreateStackRequest.py
aliyunsdkros/request/v20150901/CreateChangeSetRequest.py
aliyunsdkros/request/v20150901/CreateStacksRequest.py
aliyunsdkros/request/v20150901/DeleteChangeSetRequest.py
aliyunsdkros/request/v20150901/DeleteStackRequest.py
aliyunsdkros/request/v20150901/DescribeChangeSetDetailRequest.py
aliyunsdkros/request/v20150901/DescribeChangeSetsRequest.py
aliyunsdkros/request/v20150901/DescribeEventsRequest.py
aliyunsdkros/request/v20150901/DescribeRegionsRequest.py
aliyunsdkros/request/v20150901/DescribeResourceDetailRequest.py
aliyunsdkros/request/v20150901/DescribeResourceTypeDetailRequest.py
aliyunsdkros/request/v20150901/DescribeResourceTypeTemplateRequest.py
aliyunsdkros/request/v20150901/DescribeResourceTypesRequest.py
aliyunsdkros/request/v20150901/DescribeResourcesRequest.py
aliyunsdkros/request/v20150901/DescribeStackDetailRequest.py
aliyunsdkros/request/v20150901/DescribeStacksRequest.py
aliyunsdkros/request/v20150901/DescribeTemplateRequest.py
aliyunsdkros/request/v20150901/DoActionsRequest.py
aliyunsdkros/request/v20150901/ExecuteChangeSetRequest.py
aliyunsdkros/request/v20150901/GetStackPolicyRequest.py
aliyunsdkros/request/v20150901/InquiryStackRequest.py
aliyunsdkros/request/v20150901/PreviewStackRequest.py
aliyunsdkros/request/v20150901/SetStackPolicyRequest.py
aliyunsdkros/request/v20150901/UpdateStackRequest.py
aliyunsdkros/request/v20150901/ValidateTemplateRequest.py
aliyunsdkros/request/v20150901/WaitConditionsRequest.py
aliyunsdkros/request/v20150901/__init__.py
aliyunsdkros/request/v20190910/CancelUpdateStackRequest.py
aliyunsdkros/request/v20190910/ContinueCreateStackRequest.py
aliyunsdkros/request/v20190910/CreateChangeSetRequest.py
aliyunsdkros/request/v20190910/CreateStackGroupRequest.py
aliyun_python_sdk_ros-3.6.0.dist-info/LICENSE
aliyun_python_sdk_ros-3.6.0.dist-info/METADATA
aliyun_python_sdk_ros-3.6.0.dist-info/WHEEL
aliyun_python_sdk_ros-3.6.0.dist-info/top_level.txt
aliyun_python_sdk_ros-3.6.0.dist-info/RECORD
